odoo/addons/web_export_view/README.rst
odoo/addons/web_export_view/__init__.py
odoo/addons/web_export_view/__manifest__.py
odoo/addons/web_export_view/controllers/__init__.py
odoo/addons/web_export_view/controllers/controllers.py
odoo/addons/web_export_view/i18n/ca.po
odoo/addons/web_export_view/i18n/da.po
odoo/addons/web_export_view/i18n/de.po
odoo/addons/web_export_view/i18n/es.po
odoo/addons/web_export_view/i18n/fr.po
odoo/addons/web_export_view/i18n/hr.po
odoo/addons/web_export_view/i18n/nl_NL.po
odoo/addons/web_export_view/i18n/pt.po
odoo/addons/web_export_view/i18n/pt_BR.po
odoo/addons/web_export_view/i18n/tr.po
odoo/addons/web_export_view/i18n/web_export_view.pot
odoo/addons/web_export_view/i18n/zh_CN.po
odoo/addons/web_export_view/readme/CONFIGURATION.rst
odoo/addons/web_export_view/readme/CONFIGURE.rst
odoo/addons/web_export_view/readme/CONTRIBUTORS.rst
odoo/addons/web_export_view/readme/DESCRIPTION.rst
odoo/addons/web_export_view/readme/ROADMAP.rst
odoo/addons/web_export_view/readme/USAGE.rst
odoo/addons/web_export_view/security/groups.xml
odoo/addons/web_export_view/static/description/icon.png
odoo/addons/web_export_view/static/description/index.html
odoo/addons/web_export_view/static/src/js/web_export_view.js
odoo/addons/web_export_view/static/src/xml/web_export_view_template.xml
odoo/addons/web_export_view/static/tests/web_export_view_tests.js
odoo/addons/web_export_view/views/web_export_view_view.xml
odoo12_addon_web_export_view-12.0.1.0.2.dist-info/METADATA
odoo12_addon_web_export_view-12.0.1.0.2.dist-info/WHEEL
odoo12_addon_web_export_view-12.0.1.0.2.dist-info/top_level.txt
odoo12_addon_web_export_view-12.0.1.0.2.dist-info/RECORD
